mailbuddy/__init__.py
mailbuddy/main.py
mailbuddy-0.1.4.dist-info/LICENSE
mailbuddy-0.1.4.dist-info/METADATA
mailbuddy-0.1.4.dist-info/WHEEL
mailbuddy-0.1.4.dist-info/RECORD
