Metadata-Version: 2.1
Name: MailBuddy
Version: 0.1.4
Summary: A utility designed to simplify the process of sending formatted emails through an SMTP server.
Author: dafty144
Author-email: contact@leojohnston.tech
Requires-Python: >=3.10,<4.0
Classifier: Programming Language :: Python :: 3
Classifier: Programming Language :: Python :: 3.10
Classifier: Programming Language :: Python :: 3.11
Classifier: Programming Language :: Python :: 3.12
